ontovis/__init__.py
ontovis/__main__.py
ontovis/main.py
ontovis/py.typed
ontovis/io/__init__.py
ontovis/io/read.py
ontovis/lib/types.py
ontovis/parser/__init__.py
ontovis/parser/parser.py
ontovis/parser/strings.py
ontovis/parser/typed_accessors.py
ontovis/parser/types.py
ontovis/templates/full.dot.jinja2
ontovis/templates/no_fields.dot.jinja2
ontovis/templates/no_groups.dot.jinja2
ontovis-1.0.0.dist-info/METADATA
ontovis-1.0.0.dist-info/WHEEL
ontovis-1.0.0.dist-info/entry_points.txt
ontovis-1.0.0.dist-info/licenses/LICENSE
ontovis-1.0.0.dist-info/RECORD
