Metadata-Version: 2.4
Name: ontovis
Version: 1.0.0
Summary: Visualize and analyze WissKI pathbuilders.
Project-URL: Homepage, https://github.com/AM-Digital-Research-Environment/ontovis
Project-URL: Documentation, https://github.com/AM-Digital-Research-Environment/ontovis/blob/main/COMMANDS.md
Project-URL: Repository, https://github.com/AM-Digital-Research-Environment/ontovis
Project-URL: Issues, https://github.com/AM-Digital-Research-Environment/ontovis/issues
Project-URL: Changelog, https://github.com/AM-Digital-Research-Environment/ontovis/blob/main/CHANGELOG.md
Author-email: Oliver Baumann <oliver.baumann@uni-bayreuth.de>
License-File: LICENSE
Classifier: Development Status :: 5 - Production/Stable
Classifier: Environment :: Console
Classifier: Intended Audience :: Developers
Classifier: Intended Audience :: Information Technology
Classifier: Intended Audience :: Science/Research
Classifier: License :: OSI Approved :: MIT License
Classifier: Programming Language :: Python :: 3.11
Classifier: Topic :: Scientific/Engineering :: Information Analysis
Classifier: Topic :: Scientific/Engineering :: Visualization
Classifier: Typing :: Typed
Requires-Python: >=3.11
Requires-Dist: jinja2>=3.1.6
Requires-Dist: networkx[default]>=3.5
Requires-Dist: pygraphviz
Requires-Dist: requests>=2.32.4
Requires-Dist: rich>=14.0.0
Requires-Dist: typer>=0.16.0
